asyncactions/__init__.py
asyncactions/utils.py
asyncactions/patches/__init__.py
asyncactions/patches/context.py
asyncactions/patches/rdd.py
asyncactions/patches/tests.py
asyncactions/patches/ml/__init__.py
asyncactions/patches/ml/base.py
asyncactions/patches/ml/tests.py
asyncactions/patches/sql/__init__.py
asyncactions/patches/sql/dataframe.py
asyncactions/patches/sql/readwriter.py
asyncactions/patches/sql/tests.py
pyspark_asyncactions-0.0.2.dist-info/METADATA
pyspark_asyncactions-0.0.2.dist-info/RECORD
pyspark_asyncactions-0.0.2.dist-info/WHEEL
pyspark_asyncactions-0.0.2.dist-info/top_level.txt
