Metadata-Version: 2.1
Name: pyspark-asyncactions
Version: 0.0.2
Summary: A proof of concept asynchronous actions for PySpark using concurent.futures
Home-page: https://github.com/zero323/pyspark-asyncactions
Author: zero323
Author-email: UNKNOWN
License: Apache 2.0
Platform: UNKNOWN
Classifier: Programming Language :: Python :: 2
Classifier: Programming Language :: Python :: 3
Classifier: Development Status :: 3 - Alpha
Classifier: License :: OSI Approved :: Apache Software License
